AHB_Lite_Slave.v
module AHB_Lite_Slave(
    input HCLK,
    input HRESETn,
    input [31:0]HADDR,
    input [31:0]HWDATA,
    input HWRITE,
    input [1:0] HTRANS,

    output reg [31:0]HRDATA,
    output HREADY,
    output HRESP
);

reg [31:0] reg0;
reg [31:0] reg1;
reg [31:0] reg2;
reg [31:0] reg3;

assign HREADY =1'b1; //NO WAIT STATES

assign HRESP = 1'b0; //OKAY RESPONSE

always@(posedge HCLK or negedge HRESETn)
begin
if(!HRESETn)
begin
reg0<=32'b0;
reg1<=32'b0;
reg2<=32'b0;
reg3<=32'b0;
HRDATA<=32'b0;
end

else
begin 

if(HTRANS[1] && HWRITE)
begin

case(HADDR)

32'h00000000: reg0<=HWDATA;
32'h00000004: reg1<=HWDATA;
32'h00000008: reg2<=HWDATA;
32'h0000000C: reg3<=HWDATA;
default: ;
endcase
end

else if(HTRANS[1]&& !HWRITE)
begin
case(HADDR)

32'h00000000: HRDATA<=reg0;
32'h00000004: HRDATA<=reg1;
32'h00000008: HRDATA<=reg2;
32'h0000000C: HRDATA<=reg3;
default: HRDATA<= 32'b0;
endcase
end
end
end 
endmodule

AHB_Lite_Slave_tb.v
`timescale 1ns/1ps

module AHB_Lite_Slave_tb;

reg HCLK;
reg HRESETn;
reg [31:0] HADDR;
reg [31:0] HWDATA;
reg HWRITE;
reg [1:0] HTRANS;

wire [31:0] HRDATA;
wire HREADY;
wire HRESP;

AHB_Lite_Slave uut(
    .HCLK(HCLK),
    .HRESETn(HRESETn),
    .HADDR(HADDR),
    .HWDATA(HWDATA),
    .HWRITE(HWRITE),
    .HTRANS(HTRANS),
    .HRDATA(HRDATA),
    .HREADY(HREADY),
    .HRESP(HRESP)
);

always #5 HCLK = ~HCLK;

initial
begin

    $dumpfile("dump.vcd");
    $dumpvars(0, AHB_Lite_Slave_tb);

    // Initialize
    HCLK = 0;
    HRESETn = 0;
    HADDR = 0;
    HWDATA = 0;
    HWRITE = 0;
    HTRANS = 2'b00;

    #10;
    HRESETn = 1;

    #10;
    HWRITE = 1;
    HTRANS = 2'b10;
    HADDR  = 32'h00000000;
    HWDATA = 32'h11111111;

    #10;
    HADDR  = 32'h00000004;
    HWDATA = 32'h22222222;

    #10;
    HADDR  = 32'h00000008;
    HWDATA = 32'h33333333;

    #10;
    HADDR  = 32'h0000000C;
    HWDATA = 32'h44444444;

 
    #10;
    HWRITE = 0;
    HADDR  = 32'h00000000;

    #10;
    HADDR  = 32'h00000004;

    #10;
    HADDR  = 32'h00000008;

    #10;
    HADDR  = 32'h0000000C;

    #20;

    $finish;

end

endmodule

dump.vcd
$date
	Wed Jul 29 00:31:57 2026
$end
$version
	Icarus Verilog
$end
$timescale
	1ps
$end
$scope module AHB_Lite_Slave_tb $end
$var wire 1 ! HREADY $end
$var wire 1 " HRESP $end
$var wire 32 # HRDATA [31:0] $end
$var reg 32 $ HADDR [31:0] $end
$var reg 1 % HCLK $end
$var reg 1 & HRESETn $end
$var reg 2 ' HTRANS [1:0] $end
$var reg 32 ( HWDATA [31:0] $end
$var reg 1 ) HWRITE $end
$scope module uut $end
$var wire 32 * HADDR [31:0] $end
$var wire 1 % HCLK $end
$var wire 1 ! HREADY $end
$var wire 1 & HRESETn $end
$var wire 1 " HRESP $end
$var wire 2 + HTRANS [1:0] $end
$var wire 32 , HWDATA [31:0] $end
$var wire 1 ) HWRITE $end
$var reg 32 - HRDATA [31:0] $end
$var reg 32 . reg0 [31:0] $end
$var reg 32 / reg1 [31:0] $end
$var reg 32 0 reg2 [31:0] $end
$var reg 32 1 reg3 [31:0] $end
$upscope $end
$upscope $end
$enddefinitions $end
$comment Show the parameter values. $end
$dumpall
$end
#0
$dumpvars
b0 1
b0 0
b0 /
b0 .
b0 -
b0 ,
b0 +
b0 *
0)
b0 (
b0 '
0&
0%
b0 $
b0 #
0"
1!
$end
#5000
1%
#10000
0%
1&
#15000
1%
#20000
0%
b10001000100010001000100010001 (
b10001000100010001000100010001 ,
b10 '
b10 +
1)
#25000
b10001000100010001000100010001 .
1%
#30000
0%
b100010001000100010001000100010 (
b100010001000100010001000100010 ,
b100 $
b100 *
#35000
b100010001000100010001000100010 /
1%
#40000
0%
b110011001100110011001100110011 (
b110011001100110011001100110011 ,
b1000 $
b1000 *
#45000
b110011001100110011001100110011 0
1%
#50000
0%
b1000100010001000100010001000100 (
b1000100010001000100010001000100 ,
b1100 $
b1100 *
#55000
b1000100010001000100010001000100 1
1%
#60000
0%
b0 $
b0 *
0)
#65000
b10001000100010001000100010001 #
b10001000100010001000100010001 -
1%
#70000
0%
b100 $
b100 *
#75000
b100010001000100010001000100010 #
b100010001000100010001000100010 -
1%
#80000
0%
b1000 $
b1000 *
#85000
b110011001100110011001100110011 #
b110011001100110011001100110011 -
1%
#90000
0%
b1100 $
b1100 *
#95000
b1000100010001000100010001000100 #
b1000100010001000100010001000100 -
1%
